pyg2o/__init__.py
pyg2o/call_repr.py
pyg2o/serialize.py
pyg2o/server.py
pyg2o/classes/__init__.py
pyg2o/classes/daedalus.py
pyg2o/classes/damage.py
pyg2o/classes/items.py
pyg2o/classes/mds.py
pyg2o/classes/sky.py
pyg2o/constants/__init__.py
pyg2o/functions/__init__.py
pyg2o/functions/chat.py
pyg2o/functions/event.py
pyg2o/functions/game.py
pyg2o/functions/math.py
pyg2o/functions/npc.py
pyg2o/functions/player.py
pyg2o/functions/pyg2o.py
pyg2o/functions/streamer.py
pyg2o/functions/waypoint.py
pyg2o-2.3.3.dist-info/licenses/LICENSE
pyg2o-2.3.3.dist-info/METADATA
pyg2o-2.3.3.dist-info/WHEEL
pyg2o-2.3.3.dist-info/top_level.txt
pyg2o-2.3.3.dist-info/RECORD
