Metadata-Version: 2.4
Name: PyG2O
Version: 2.3.3
Requires-Python: >=3.13
License-File: LICENSE
Requires-Dist: loguru>=0.7.3
Requires-Dist: websockets>=15.0.1
Dynamic: license-file
